optcom/__init__.py
optcom/config.py
optcom/domain.py
optcom/field.py
optcom/layout.py
optcom/components/__init__.py
optcom/components/abstract_component.py
optcom/components/abstract_fiber_amp.py
optcom/components/abstract_fiber_amp_2levels.py
optcom/components/abstract_pass_comp.py
optcom/components/abstract_start_comp.py
optcom/components/cw.py
optcom/components/fiber.py
optcom/components/fiber_coupler.py
optcom/components/fiber_yb.py
optcom/components/flat_top_filter.py
optcom/components/gaussian.py
optcom/components/gaussian_filter.py
optcom/components/generic_filter.py
optcom/components/ideal_amplifier.py
optcom/components/ideal_combiner.py
optcom/components/ideal_coupler.py
optcom/components/ideal_divider.py
optcom/components/ideal_filter.py
optcom/components/ideal_isolator.py
optcom/components/ideal_mzm.py
optcom/components/ideal_phase_mod.py
optcom/components/load_field.py
optcom/components/load_field_from_file.py
optcom/components/port.py
optcom/components/save_field.py
optcom/components/save_field_to_file.py
optcom/components/sech.py
optcom/components/soliton.py
optcom/constraints/__init__.py
optcom/constraints/abstract_constraint.py
optcom/constraints/constraint_coprop.py
optcom/constraints/constraint_max_pass_port.py
optcom/constraints/constraint_port_in.py
optcom/constraints/constraint_port_valid.py
optcom/constraints/constraint_waiting.py
optcom/effects/__init__.py
optcom/effects/absorption.py
optcom/effects/abstract_effect.py
optcom/effects/abstract_effect_taylor.py
optcom/effects/active_fiber_photon_process.py
optcom/effects/asymmetry.py
optcom/effects/attenuation.py
optcom/effects/coupling.py
optcom/effects/dispersion.py
optcom/effects/emission.py
optcom/effects/gain.py
optcom/effects/gain_saturation.py
optcom/effects/kerr.py
optcom/effects/pump.py
optcom/effects/raman.py
optcom/effects/raman_approx.py
optcom/effects/relaxation.py
optcom/effects/self_steepening.py
optcom/effects/self_steepening_approx.py
optcom/equations/__init__.py
optcom-0.3.6.dist-info/LICENSE
optcom-0.3.6.dist-info/METADATA
optcom-0.3.6.dist-info/WHEEL
optcom-0.3.6.dist-info/top_level.txt
optcom-0.3.6.dist-info/RECORD
