Metadata-Version: 2.1
Name: optcom
Version: 0.3.6
Summary: Optical System Simulator
Home-page: https://github.com/optcom-org/optcom
Author: Sacha Medaer
Author-email: sacha.medaer@optcom.org
License: Apache License 2.0
Download-URL: https://github.com/optcom-org/optcom/archive/v0.3.6.tar.gz
Platform: UNKNOWN
Classifier: Natural Language :: English
Classifier: Intended Audience :: Science/Research
Classifier: License :: OSI Approved :: Apache Software License
Classifier: Programming Language :: Python :: 3
Classifier: Programming Language :: Python :: 3.7
Requires-Python: >=3.7.0
